tidy/__init__.py
tidy/cli/__init__.py
tidy/cli/cli.py
tidy/cli/commands/__init__.py
tidy/cli/commands/sweep.py
tidy/cli/options.py
tidy/config/__init__.py
tidy/config/constants.py
tidy/config/tidy_config.py
tidy/manifest/__init__.py
tidy/manifest/utils/__init__.py
tidy/manifest/utils/config_block.py
tidy/manifest/utils/dag.py
tidy/manifest/utils/types.py
tidy/manifest/v10/bases/__init__.py
tidy/manifest/v10/bases/column_info.py
tidy/manifest/v10/bases/contract.py
tidy/manifest/v10/bases/defer_relation.py
tidy/manifest/v10/bases/depends_on.py
tidy/manifest/v10/bases/docs.py
tidy/manifest/v10/bases/enums.py
tidy/manifest/v10/bases/file_hash.py
tidy/manifest/v10/bases/hook.py
tidy/manifest/v10/bases/injected_cte.py
tidy/manifest/v10/bases/node_config.py
tidy/manifest/v10/bases/owner.py
tidy/manifest/v10/bases/ref_args.py
tidy/manifest/v10/bases/source_file_metadata.py
tidy/manifest/v10/bases/where_filter_intersection.py
tidy/manifest/v10/documentation/__init__.py
tidy/manifest/v10/documentation/documentation.py
tidy/manifest/v10/exposures/__init__.py
tidy/manifest/v10/exposures/exposure.py
tidy/manifest/v10/exposures/exposure_config.py
tidy/manifest/v10/groups/__init__.py
tidy/manifest/v10/groups/group.py
tidy/manifest/v10/macros/__init__.py
tidy/manifest/v10/macros/macro.py
tidy/manifest/v10/macros/macro_argument.py
tidy/manifest/v10/macros/macro_depends_on.py
tidy/manifest/v10/manifest.py
tidy/manifest/v10/metadata/__init__.py
tidy/manifest/v10/metadata/metadata.py
tidy/manifest/v10/metrics/__init__.py
tidy/manifest/v10/metrics/metric.py
tidy/manifest/v10/metrics/metric_config.py
tidy/manifest/v10/metrics/metric_type_params.py
tidy/manifest/v10/metrics/where_filter.py
tidy/manifest/v10/nodes/__init__.py
tidy/manifest/v10/nodes/analysis/__init__.py
tidy/manifest/v10/nodes/analysis/analysis.py
tidy/manifest/v10/nodes/hooks/__init__.py
tidy/manifest/v10/nodes/hooks/hook.py
tidy/manifest/v10/nodes/models/__init__.py
tidy/manifest/v10/nodes/models/model.py
dbt_tidy-0.6.0.dist-info/LICENSE
dbt_tidy-0.6.0.dist-info/METADATA
dbt_tidy-0.6.0.dist-info/WHEEL
dbt_tidy-0.6.0.dist-info/entry_points.txt
dbt_tidy-0.6.0.dist-info/RECORD
